LICENSE
README.md
pyproject.toml
setup.py
src/pylong/__init__.py
src/pylong/main.py
src/pylong/run.py
src/pylong.egg-info/PKG-INFO
src/pylong.egg-info/SOURCES.txt
src/pylong.egg-info/dependency_links.txt
src/pylong.egg-info/requires.txt
src/pylong.egg-info/top_level.txt
src/pylong/api/__init__.py
src/pylong/api/common/__init__.py
src/pylong/api/common/allure_opt.py
src/pylong/api/common/common_argv.py
src/pylong/api/common/common_assert.py
src/pylong/api/common/http_case.py
src/pylong/api/common/playground.py
src/pylong/api/common/pre_request.py
src/pylong/api/common/pytest_run.py
src/pylong/api/common/swagger_api.py
src/pylong/api/common/tables_query.py
src/pylong/api/models/__init__.py
src/pylong/api/models/cases_collect.py
src/pylong/api/models/cases_execute.py
src/pylong/api/routes/__init__.py
src/pylong/api/routes/api_case.py
src/pylong/api/routes/api_test.py
src/pylong/api/utils/__init__.py
src/pylong/api/utils/api.py
src/pylong/api/utils/assertion.py
src/pylong/api/utils/client.py
src/pylong/api/utils/config.py
src/pylong/api/utils/error.py
src/pylong/api/utils/extractor.py
src/pylong/api/utils/file_reader.py
src/pylong/api/utils/file_writer.py
src/pylong/api/utils/generator.py
src/pylong/api/utils/injson.py
src/pylong/api/utils/log.py
src/pylong/api/utils/responses.py
src/pylong/api/utils/sql.py
src/pylong/api/utils/support.py
src/pylong/thirdparty/__init__.py
src/pylong/thirdparty/PLATFORM/__init__.py
src/pylong/thirdparty/PLATFORM/case_manage.py
src/pylong/thirdparty/PLATFORM/group_manage.py
src/pylong/thirdparty/PLATFORM/project_manage.py
src/pylong/thirdparty/PLATFORM/result_manage.py