Metadata-Version: 2.1
Name: pylong
Version: 0.0.0
Summary: use yaml to combination params for pytest collect test cases
Home-page: https://github.com/pypa/sampleproject
Author: jiukun
Author-email: jiukun9291@gmail.com
License: UNKNOWN
Project-URL: Bug Tracker, https://github.com/pypa/sampleproject/issues
Platform: UNKNOWN
Classifier: Programming Language :: Python :: 3.7
Classifier: License :: OSI Approved :: MIT License
Classifier: Operating System :: OS Independent
Requires-Python: >=3.7
